{
  "__data_type": "UTI ",
  "AddCost": {
    "type": "dword",
    "value": 250
  },
  "BaseItem": {
    "type": "int",
    "value": 110
  },
  "Charges": {
    "type": "byte",
    "value": 0
  },
  "Comment": {
    "type": "cexostring",
    "value": "\r\n"
  },
  "Cost": {
    "type": "dword",
    "value": 250
  },
  "Cursed": {
    "type": "byte",
    "value": 0
  },
  "DescIdentified": {
    "type": "cexolocstring",
    "value": {
      "0": "These are matching crosshairs, which are helpful for improving firing accuracy in smoke powder weapons.\n\nIf used to modify a smoke powder weapon, Crosshairs will take up 1 modification slot for each one added.\n\nProperty: +1 Attack Bonus",
      "id": 83778
    }
  },
  "Description": {
    "type": "cexolocstring",
    "value": {
      "0": ""
    }
  },
  "Identified": {
    "type": "byte",
    "value": 1
  },
  "LocalizedName": {
    "type": "cexolocstring",
    "value": {
      "0": "Barrel Upgrade: Crosshair",
      "id": 83777
    }
  },
  "ModelPart1": {
    "type": "byte",
    "value": 86
  },
  "PaletteID": {
    "type": "byte",
    "value": 64
  },
  "Plot": {
    "type": "byte",
    "value": 0
  },
  "PropertiesList": {
    "type": "list",
    "value": []
  },
  "StackSize": {
    "type": "word",
    "value": 1
  },
  "Stolen": {
    "type": "byte",
    "value": 0
  },
  "Tag": {
    "type": "cexostring",
    "value": "te_fireupg_001"
  },
  "TemplateResRef": {
    "type": "resref",
    "value": "te_fireupg_001"
  }
}
