{
  "__data_type": "UTI ",
  "AddCost": {
    "type": "dword",
    "value": 154
  },
  "ArmorPart_Belt": {
    "type": "byte",
    "value": 63
  },
  "ArmorPart_LBicep": {
    "type": "byte",
    "value": 125
  },
  "ArmorPart_LFArm": {
    "type": "byte",
    "value": 4
  },
  "ArmorPart_LFoot": {
    "type": "byte",
    "value": 151
  },
  "ArmorPart_LHand": {
    "type": "byte",
    "value": 8
  },
  "ArmorPart_LShin": {
    "type": "byte",
    "value": 15
  },
  "ArmorPart_LShoul": {
    "type": "byte",
    "value": 99
  },
  "ArmorPart_LThigh": {
    "type": "byte",
    "value": 162
  },
  "ArmorPart_Neck": {
    "type": "byte",
    "value": 1
  },
  "ArmorPart_Pelvis": {
    "type": "byte",
    "value": 161
  },
  "ArmorPart_RBicep": {
    "type": "byte",
    "value": 125
  },
  "ArmorPart_RFArm": {
    "type": "byte",
    "value": 4
  },
  "ArmorPart_RFoot": {
    "type": "byte",
    "value": 151
  },
  "ArmorPart_RHand": {
    "type": "byte",
    "value": 8
  },
  "ArmorPart_Robe": {
    "type": "byte",
    "value": 0
  },
  "ArmorPart_RShin": {
    "type": "byte",
    "value": 15
  },
  "ArmorPart_RShoul": {
    "type": "byte",
    "value": 99
  },
  "ArmorPart_RThigh": {
    "type": "byte",
    "value": 162
  },
  "ArmorPart_Torso": {
    "type": "byte",
    "value": 176
  },
  "BaseItem": {
    "type": "int",
    "value": 16
  },
  "Charges": {
    "type": "byte",
    "value": 0
  },
  "Cloth1Color": {
    "type": "byte",
    "value": 23
  },
  "Cloth2Color": {
    "type": "byte",
    "value": 23
  },
  "Comment": {
    "type": "cexostring",
    "value": ""
  },
  "Cost": {
    "type": "dword",
    "value": 212
  },
  "Cursed": {
    "type": "byte",
    "value": 0
  },
  "DescIdentified": {
    "type": "cexolocstring",
    "value": {
      "0": "The Kahkashan are innumerable. A sweet promise awaits those who seek to count the glittering stars in the night sky.",
      "id": 13776
    }
  },
  "Description": {
    "type": "cexolocstring",
    "value": {
      "0": "Piecemeal or complete armors of this type offer basic protection, equivalent to hardened leather."
    }
  },
  "Identified": {
    "type": "byte",
    "value": 0
  },
  "Leather1Color": {
    "type": "byte",
    "value": 127
  },
  "Leather2Color": {
    "type": "byte",
    "value": 126
  },
  "LocalizedName": {
    "type": "cexolocstring",
    "value": {
      "0": "Kahkashan Garb (Male)",
      "id": 13790
    }
  },
  "Metal1Color": {
    "type": "byte",
    "value": 1
  },
  "Metal2Color": {
    "type": "byte",
    "value": 127
  },
  "PaletteID": {
    "type": "byte",
    "value": 190
  },
  "Plot": {
    "type": "byte",
    "value": 0
  },
  "PropertiesList": {
    "type": "list",
    "value": [
      {
        "__struct_id": 0,
        "ChanceAppear": {
          "type": "byte",
          "value": 100
        },
        "CostTable": {
          "type": "byte",
          "value": 28
        },
        "CostValue": {
          "type": "word",
          "value": 9
        },
        "Param1": {
          "type": "byte",
          "value": 255
        },
        "Param1Value": {
          "type": "byte",
          "value": 0
        },
        "PropertyName": {
          "type": "word",
          "value": 85
        },
        "Subtype": {
          "type": "word",
          "value": 0
        }
      },
      {
        "__struct_id": 0,
        "ChanceAppear": {
          "type": "byte",
          "value": 100
        },
        "CostTable": {
          "type": "byte",
          "value": 29
        },
        "CostValue": {
          "type": "word",
          "value": 11
        },
        "Param1": {
          "type": "byte",
          "value": 255
        },
        "Param1Value": {
          "type": "byte",
          "value": 0
        },
        "PropertyName": {
          "type": "word",
          "value": 86
        },
        "Subtype": {
          "type": "word",
          "value": 0
        }
      },
      {
        "__struct_id": 0,
        "ChanceAppear": {
          "type": "byte",
          "value": 100
        },
        "CostTable": {
          "type": "byte",
          "value": 25
        },
        "CostValue": {
          "type": "word",
          "value": 2
        },
        "Param1": {
          "type": "byte",
          "value": 255
        },
        "Param1Value": {
          "type": "byte",
          "value": 0
        },
        "PropertyName": {
          "type": "word",
          "value": 52
        },
        "Subtype": {
          "type": "word",
          "value": 21
        }
      }
    ]
  },
  "StackSize": {
    "type": "word",
    "value": 1
  },
  "Stolen": {
    "type": "byte",
    "value": 1
  },
  "Tag": {
    "type": "cexostring",
    "value": "te_item_8749"
  },
  "TemplateResRef": {
    "type": "resref",
    "value": "te_item_8749"
  },
  "VarTable": {
    "type": "list",
    "value": [
      {
        "__struct_id": 0,
        "Name": {
          "type": "cexostring",
          "value": "Material"
        },
        "Type": {
          "type": "dword",
          "value": 1
        },
        "Value": {
          "type": "int",
          "value": 1
        }
      },
      {
        "__struct_id": 0,
        "Name": {
          "type": "cexostring",
          "value": "Masterwork"
        },
        "Type": {
          "type": "dword",
          "value": 1
        },
        "Value": {
          "type": "int",
          "value": 1
        }
      }
    ]
  }
}
