{
  "__data_type": "UTI ",
  "AddCost": {
    "type": "dword",
    "value": 1000
  },
  "BaseItem": {
    "type": "int",
    "value": 112
  },
  "Charges": {
    "type": "byte",
    "value": 0
  },
  "Comment": {
    "type": "cexostring",
    "value": ""
  },
  "Cost": {
    "type": "dword",
    "value": 1000
  },
  "Cursed": {
    "type": "byte",
    "value": 0
  },
  "DescIdentified": {
    "type": "cexolocstring",
    "value": {
      "0": "This is a Holy Chalice, intended for use by paladins to imbue their Holy Avengers with anti-outsider properties.\n\nA Holy Chalice takes up 1/10 available modification slots.",
      "id": 90548
    }
  },
  "Description": {
    "type": "cexolocstring",
    "value": {
      "0": ""
    }
  },
  "Identified": {
    "type": "byte",
    "value": 1
  },
  "LocalizedName": {
    "type": "cexolocstring",
    "value": {
      "0": "Holy Chalice",
      "id": 90547
    }
  },
  "ModelPart1": {
    "type": "byte",
    "value": 27
  },
  "PaletteID": {
    "type": "byte",
    "value": 20
  },
  "Plot": {
    "type": "byte",
    "value": 0
  },
  "PropertiesList": {
    "type": "list",
    "value": []
  },
  "StackSize": {
    "type": "word",
    "value": 1
  },
  "Stolen": {
    "type": "byte",
    "value": 1
  },
  "Tag": {
    "type": "cexostring",
    "value": "te_palupgr012"
  },
  "TemplateResRef": {
    "type": "resref",
    "value": "te_palupgr012"
  }
}
